<?xml version="1.0" encoding="utf-8"?>

<!DOCTYPE grid [
  <!ENTITY % GridInitialize SYSTEM "..\Include\Grid.ent">
  %GridInitialize;

  <!ENTITY XMLStandardDetailToolbar SYSTEM "..\Include\XML\StandardDetailToolbar.xml">
  <!ENTITY XMLUserDefinedHiddenFields SYSTEM "..\Include\XML\UserDefinedHiddenFields.txt">
  <!ENTITY XMLUserDefinedHiddenViews SYSTEM "..\Include\XML\UserDefinedHiddenViews.txt">
  <!ENTITY XMLFlowGridCommand SYSTEM "..\Include\XML\FlowGridCommand.txt">
  <!ENTITY ScriptFlowGridFunction SYSTEM "..\Include\Javascript\FlowGridFunction.txt">

  <!ENTITY Identity "SupplierAllocation">

  <!ENTITY FlowGridTagField "chon">

  <!ENTITY % CheckRelative SYSTEM "..\Include\CheckRelative.ent">
  %CheckRelative;
  <!ENTITY CheckRelativeParameter "'SARequisitionGrid', 'Grid', 'SATran'">
  <!ENTITY CheckRelativeQuery "
    select top 0 @@fieldExternal from d91$000000 a, m91$000000 b, dmgia3 c, dmkh d, dmvt e
    return
">
]>

<grid table="d91$000000" code="stt_rec" order="stt_rec, line_nbr" type="Detail" freezeColumns="3" id="PR1" xmlns="urn:schemas-fast-com:data-grid">
  <title v="" e=""></title>
  <subTitle v="" e=""></subTitle>
  <partition table="c91$000000" prime="d91$" inquiry="i91$" field="ngay_ct" expression="convert(char(6), {0}, 112)" increase="dateadd(month, 1, {0})" default="000000"/>

  <fields>
    <field name="ma_kh" allowNulls="false" readOnly="true" width="100" aliasName="c">
      <header v="Mã ncc" e="Supplier ID"></header>
    </field>
    <field name="ten_kh%l" readOnly="true" external="true" defaultValue="''" width="300" aliasName="d">
      <header v="Tên nhà cung cấp" e="Supplier Name"></header>
    </field>
    <field name="chon" type="Boolean" external="true" allowContain="true" defaultValue="0" width="60">
      <header v="Chọn" e="Select"></header>
      <items style="CheckBox"/>
      <clientScript><![CDATA[onclick="onClick$]]>&Identity;<![CDATA[$Calculate(this);"]]></clientScript>
    </field>

    <field name="so_luong0" type="Decimal" dataFormatString="@quantityInputFormat" defaultValue="0" clientDefault="0" width="80" external="true">
      <header v="Sl đặt hàng" e="Order Q'ty"></header>
      <items style="Numeric"/>
    </field>

    <field name="sl_dh" type="Decimal" dataFormatString="@quantityViewFormat" readOnly="true" defaultValue="0" clientDefault="0" width="80">
      <header v="Sl đã đặt" e="Ordered Q'ty"></header>
      <items style="Numeric"/>
    </field>

    <field name="gia_nt" readOnly="true" type="Decimal" dataFormatString="@foreignCurrencyPriceViewFormat" clientDefault="0" width="100" aliasName="c">
      <header v="Giá" e="Sales Price"></header>
      <items style="Numeric"/>
    </field>
    <field name="ma_nt" readOnly="true" width="60" aliasName="c">
      <header v="Mã nt" e="Currency Code"></header>
    </field>
    <field name="ngay_ct1" type="DateTime" dataFormatString="@datetimeFormat" readOnly="true" width="80" align="left" aliasName="c">
      <header v="Hiệu lực từ" e="Effective from"></header>
    </field>
    <field name="ngay_ct2" type="DateTime" dataFormatString="@datetimeFormat" readOnly="true" width="80" align="left" aliasName="c">
      <header v="Đến ngày" e="Effective To"></header>
    </field>
    <field name="tg_th" type="Decimal" dataFormatString="@quantityViewFormat" clientDefault="0" width="80" readOnly="true" aliasName="c">
      <header v="Thời gian thực hiện" e="Lead Time"></header>
      <items style="Numeric"/>
    </field>
    <field name="ghi_chu" clientDefault="0" width="300" aliasName="a">
      <header v="Ghi chú" e="Note"></header>
    </field>
    <field name="he_so1" type="Decimal" hidden="true" width="0" aliasName="c">
      <header v="" e=""></header>
      <items style="Numeric"/>
    </field>
    <field name="so_luong1" type="Decimal" dataFormatString="@quantityViewFormat" clientDefault="0" width="80" readOnly="true" aliasName="c">
      <header v="Số lượng từ" e="Quantity from"></header>
      <items style="Numeric"/>
    </field>
    <field name="so_luong2" type="Decimal" dataFormatString="@quantityViewFormat" clientDefault="0" width="80" readOnly="true" aliasName="c">
      <header v="Đến" e="Quantity to"></header>
      <items style="Numeric"/>
    </field>
    <field name="sl_min" type="Decimal" dataFormatString="@quantityViewFormat" clientDefault="0" width="80" readOnly="true" aliasName="c">
      <header v="Sl tối thiểu" e="Min Quantity"></header>
      <items style="Numeric"/>
    </field>
    <field name="sl_max" type="Decimal" dataFormatString="@quantityViewFormat" clientDefault="0" width="80" readOnly="true" aliasName="c">
      <header v="Sl tối đa" e="Max Quantity"></header>
      <items style="Numeric"/>
    </field>

    <field name="ma_vt" allowNulls="false" hidden="true" width="0" aliasName="a">
      <header v="" e=""></header>
    </field>
    <field name="ten_vt%l" readOnly="true" external="true" defaultValue="''" hidden="true" width="0" aliasName="e">
      <header v="" e=""></header>
    </field>
    <field name="dvt" allowNulls="false" hidden="true" width="0" aliasName="a">
      <header v="" e=""></header>
    </field>
    <field name="he_so" type="Decimal" dataFormatString="&CoefficientInputFormat;" allowNulls="false" hidden="true" width="0" aliasName="a">
      <header v="" e=""></header>
    </field>
    <field name="sl_duyet" type="Decimal" dataFormatString="@quantityViewFormat" clientDefault="0" width="0" hidden="true" aliasName="a">
      <header v="" e=""></header>
      <items style="Numeric"/>
    </field>
    <field name="ngay_yc" type="DateTime" dataFormatString="@datetimeFormat" hidden="true" width="0" align="left" aliasName="a">
      <header v="" e=""></header>
    </field>
    <field name="stt_rec" allowNulls="false" hidden="true" width="0" aliasName="a">
      <header v="" e=""></header>
    </field>
    <field name="stt_rec0" allowNulls="false" hidden="true" width="0" aliasName="a">
      <header v="" e=""></header>
    </field>

  </fields>

  <views>
    <view id="Grid">
      <field name="ma_kh"/>
      <field name="ten_kh%l"/>
      <field name="chon"/>
      <field name="so_luong0"/>
      <field name="sl_dh"/>
      <field name="gia_nt"/>
      <field name="ma_nt"/>
      <field name="ngay_ct1"/>
      <field name="ngay_ct2"/>
      <field name="tg_th"/>
      <field name="ghi_chu"/>

      <field name="he_so1"/>
      <field name="so_luong1"/>
      <field name="so_luong2"/>
      <field name="sl_min"/>
      <field name="sl_max"/>

      <field name="sl_duyet"/>
      <field name="ma_vt"/>
      <field name="ten_vt%l"/>
      <field name="dvt"/>
      <field name="he_so"/>
      <field name="ngay_yc"/>
      <field name="stt_rec"/>
      <field name="stt_rec0"/>
    </view>
  </views>

  <commands>
    &XMLFlowGridCommand;

    <command event="Closing">
      <text>
        <![CDATA[select 'dispose$GridVoucherDetail$(this);' as message
return]]>
      </text>
    </command>
  </commands>

  <script>
    <text>
      <![CDATA[
function load$]]>&Identity;<![CDATA[Grid$(g) {
  var f = g.get_element().parentForm;
  if (g._rowCount > 0) g._focusWhenTabChanged();
    else try {$get(String.format('{0}_updateDlgCancel', f._id)).focus();} catch (ex) {}
  g.add_itemValueChanged(onChange$]]>&Identity;<![CDATA[$GridVoucherDetail$);
  g.add_commandEvent(on$]]>&Identity;<![CDATA[GridVoucherDetail$ExecuteCommand);
}
function scatter$]]>&Identity;<![CDATA[Grid$(g) {g._memvars = [];}
function dispose$GridVoucherDetail$(g) {
  try {g.remove_commandEvent(on$]]>&Identity;<![CDATA[GridVoucherDetail$ExecuteCommand);} catch (ex) {}
  try {g.remove_itemValueChanged(onChange$]]>&Identity;<![CDATA[$GridVoucherDetail$);} catch (ex) {}
}
function on$]]>&Identity;<![CDATA[GridVoucherDetail$ExecuteCommand(sender, e) {
  var action = e.type.Action, g = sender, f = g.get_element().parentForm;
  switch (action) {
    case 'Check':
      var s = String.format('({0}==0)||(({1}{5}{1}<={0})&&({2}{5}{2}<={0})&&({3}{5}{3}>={0})&&({4}{5}{4}>={0}))', '[so_luong0]', '[so_luong1]', '[sl_min]', '[so_luong2]', '[sl_max]', '==0||');
      g.validRowExpression('so_luong0', s);
      break;
    default:
      break;
  }
}
function onChange$]]>&Identity;<![CDATA[$GridVoucherDetail$(sender, eventArgs) {
  var o = eventArgs.get_object(), g = o.grid, name = o.field.Name;
  switch (name) {
    case 'so_luong0':
      g.executeAggregate([['t_so_luong', 'so_luong0']]);
      break;
    default:
      break;
  }
}
function onClick$]]>&Identity;<![CDATA[$Calculate(o) {
  var g = o.grid, a = o.id.split('_inputCell_'), r = a[1].split('.')[0];
  if (!g) g = $find(a[0]);
  f = g.get_element().parentForm;
  var l = g._getColumnOrder(']]>&FlowGridTagField;<![CDATA['), l0 = g._getColumnOrder('so_luong0'), l1 = g._getColumnOrder('sl_dh');
  var a = f.getItemValue('sl_duyet'), b = 0, c = g._getItemValue(1, l1);

  for (var i = 1; i <= g._rowCount; i++) {b = b + g._getItemValue(i, l0);}
  g._setItemValue(r, l0, o.checked ? a - (b + c): 0);
  g.executeAggregate([['t_so_luong', 'so_luong0']]);
}
]]>
    </text>
  </script>

  <queries>
    <query event="Loading">
      <text>
        &CheckRelativeProcess;
        <![CDATA[
select top 0 @@fieldExternal into #temp from d91$000000 a
  left join m91$000000 b on b.stt_rec = a.stt_rec	join dmgia3 c on c.ma_vt = a.ma_vt
  left join dmkh d on d.ma_kh = c.ma_kh left join dmvt e on e.ma_vt = a.ma_vt

declare @q nvarchar(4000), @p char(6)
select @p = convert(char(6), ngay_ct, 112) from c91$000000 where stt_rec = @stt_rec
set @q = 'insert into #temp select distinct @@fieldExternal from d91$' + @p + ' a left join m91$' + @p + ' b on a.stt_rec = b.stt_rec'
set @q = @q + ' join dmgia3 c on a.ma_vt = c.ma_vt left join dmkh d on d.ma_kh = c.ma_kh left join dmvt e on e.ma_vt = a.ma_vt'
set @q = @q + ' where a.stt_rec = ''' + replace(@stt_rec, '''', '''''') + ''' and a.ma_vt = ''' + replace(@ma_vt, '''', '''''') + ''''
set @q = @q + ' and a.sl_duyet > 0 and a.xstatus in (''2'', ''5'') and ''' + replace(@sa_date, '''', '') + ''' between c.ngay_ct1 and c.ngay_ct2'
set @q = @q + ' order by ma_kh'
exec sp_executesql @q

declare @n1 int, @n2 int
select @n1 = cast(rtrim(val) as int) from options where name = 'm_round_sl'
select @n2 = cast(rtrim(val) as int) from options where name = 'm_round_gia_nt'
update #temp set so_luong1 = round(so_luong1*he_so1/he_so, @n1),
  so_luong2 = round(so_luong2*he_so1/he_so, @n1),
  sl_min = round(sl_min*he_so1/he_so, @n1),
  sl_max = round(sl_max*he_so1/he_so, @n1)
where he_so <> 0

update #temp set gia_nt = round(gia_nt*he_so/he_so1, @n2) where he_so1 <> 0
update #temp set so_luong1 = 0, so_luong2 = 0, sl_min = 0, sl_max = 0 where he_so = 0
update #temp set gia_nt = 0 where he_so1 = 0

select * from #temp order by ma_kh
drop table #temp
]]>
      </text>
    </query>
  </queries>

  <toolbar>
    <button command="Export">
      <title v="Toolbar.Export" e="Toolbar.Export"></title>
    </button>
    <button command="Freeze">
      <title v="Toolbar.Freeze" e="Toolbar.Freeze"></title>
    </button>
  </toolbar>

</grid>