<?xml version="1.0" encoding="utf-8"?>

<!DOCTYPE import [
  <!ENTITY Error "
if @r is not null begin
  select '' as message, @field as field, @r as record
  return
end
">
  <!ENTITY And "&#13;">
  <!ENTITY Checking "@@checking">
  <!ENTITY Inserting "@@inserting">
  <!ENTITY Updating "@@updating">
]>

<import xmlns="urn:schemas-fast-com:data-import">
  <setting>
    <startRow value="6"/>
    <maxFileSize value="10"/>
    <uploadTimeOut value="120"/>
    <importRecordTimeout value="1740"/>
    <allowFileExtension value="^(.XLSX)$"/>
    <onProcessFail value="parent.on$JobAccumulationBalanceImportForm$Fail(this.frameElement)"/>
    <onProcessComplete value="parent.on$JobAccumulationBalanceImportForm$Complete(this.frameElement)"/>
    <uploadContentType value="application/ms-excel;application/vnd.openxmlformats-officedocument.spreadsheetml.sheet" />
    <baseTable value="lkvv"/>
    <table value="lkvv" alias="a"/>
    <temporary value="#k" alias="b"/>
  </setting>

  <fields identity="true" name="stt">
    <field name="ma_dvcs" column="A" isPrimaryKey="true" allowNulls="false" upperCase="true" updateValue="None" check="ma_dvcs not in (select ma_dvcs from dmdvcs where status = '1')&And;ma_dvcs in (select distinct ma_dvcs from dmdvcsks where year(ngay_ks) >= @year)&And;not exists(select 1 from lkvv b where @@table.ma_dvcs = b.ma_dvcs and @@table.tk = b.tk and @@table.ma_vv = b.ma_vv and b.nam = @year) and @@table.ma_dvcs not in (select distinct ma_dvcs from sysunitrights where user_id = @user and r_new = 1)&And;exists(select 1 from lkvv b where @@table.ma_dvcs = b.ma_dvcs and @@table.tk = b.tk and @@table.ma_vv = b.ma_vv and b.nam = @year) and @@table.ma_dvcs not in (select distinct ma_dvcs from sysunitrights where user_id = @user and r_edit = 1)" condition="&And;&And;if (@admin &lt;&gt; 1) begin&And;if (@admin &lt;&gt; 1 and @type = '1') begin" tag="&And;&And;end&And;end"/>
    <field name="tk" column="B" isPrimaryKey="true" allowNulls="false" upperCase="true" updateValue="None" check="tk not in (select tk_lkvv from dmtklkvv)"/>
    <field name="ma_vv" column="C" isPrimaryKey="true" allowNulls="false" upperCase="true" updateValue="None" check="ma_vv not in (select ma_vv from dmvv)"/>
    <field name="lk_no" column="E" type="Decimal"/>
    <field name="lk_co" column="F" type="Decimal"/>
    <field name="lk_no_dk" column="G" type="Decimal"/>
    <field name="lk_co_dk" column="H" type="Decimal"/>
    <field name="lk_no_nt" column="I" type="Decimal"/>
    <field name="lk_co_nt" column="J" type="Decimal"/>
    <field name="lk_no_dk_nt" column="K" type="Decimal"/>
    <field name="lk_co_dk_nt" column="L" type="Decimal"/>

    <field name="nam" column="None" insertValue="@year" type="Decimal" updateValue="None"/>
    <field name="datetime0" column="None" type="DateTime" insertValue="getdate()" updateValue="None"/>
    <field name="datetime2" column="None" type="DateTime" insertValue="getdate()" updateValue="getdate()"/>
    <field name="user_id0" column="None" type="Int" insertValue="@@userID" updateValue="None"/>
    <field name="user_id2" column="None" type="Int" insertValue="@@userID" updateValue="@@userID"/>
  </fields>

  <processing>
    <text>
      <![CDATA[
declare @q nvarchar(4000), @message nvarchar(4000), @field varchar(32), @user int, @admin bit, @unit varchar(32), @year int, @r int, @inputYearOpening bit
select @admin = @@admin, @user = @@userID, @unit = @@unit, @year = nam_bd from dmstt
select @inputYearOpening = case when month(ngay_ky1) = month(ngay_dn2) and day(ngay_ky1) = day(ngay_dn2) then 0 else 1 end from dmstt

if @admin <> 1 begin
  if @type = '1' begin
    if @@sysDatabaseName.dbo.FastBusiness$System$GetAuthorize(@admin, @user, 'JobAccumulationBalance', 'Edit') = 0 select @type = '0'
  end
end

-- Checking
]]>&Checking;<![CDATA[

if @inputYearOpening = 0 begin
  update @@table set lk_no_dk = 0, lk_co_dk = 0, lk_no_dk_nt = 0, lk_co_dk_nt = 0
end

if @type = '0' delete @@table from @@table a where exists(select 1 from lkvv b where a.ma_dvcs = b.ma_dvcs and a.tk = b.tk and a.ma_vv = b.ma_vv and b.nam = @year)

select a.* into #k from @@table a join lkvv b on a.ma_dvcs = b.ma_dvcs and a.tk = b.tk and a.ma_vv = b.ma_vv where b.nam = @year
delete @@table from @@table a where exists(select 1 from #k b where a.ma_dvcs = b.ma_dvcs and a.tk = b.tk and a.ma_vv = b.ma_vv)

-- Insert
]]>&Inserting;<![CDATA[
-- Update
if @type = '1' begin ]]>&Updating;<![CDATA[ where a.nam = @year end
]]>
    </text>
  </processing>
</import>